nested_dict_tools/__about__.py
nested_dict_tools/__init__.py
nested_dict_tools/_core.py
nested_dict_tools/py.typed
nested_dict_tools-0.4.1.dist-info/METADATA
nested_dict_tools-0.4.1.dist-info/WHEEL
nested_dict_tools-0.4.1.dist-info/licenses/LICENSE
nested_dict_tools-0.4.1.dist-info/RECORD
