Metadata-Version: 2.3
Name: nested_dict_tools
Version: 0.4.1
Summary: Utilities for Python nested dictionaries.
Project-URL: Repository, https://github.com/Kajiih/nested_dict_tools
Project-URL: Issues, https://github.com/Kajiih/nested_dict_tools/issues
Author-email: Kajih <itskajih@gmail.com>
License: MIT License
Keywords: nested dictionary,python,tools,utils
Classifier: Development Status :: 4 - Beta
Classifier: License :: OSI Approved :: MIT License
Classifier: Natural Language :: English
Classifier: Programming Language :: Python
Classifier: Programming Language :: Python :: 3.12
Classifier: Programming Language :: Python :: 3.13
Classifier: Programming Language :: Python :: Implementation :: CPython
Requires-Python: >=3.12
